slither_lsp/__init__.py
slither_lsp/__main__.py
slither_lsp/app/__init__.py
slither_lsp/app/app.py
slither_lsp/app/slither_server.py
slither_lsp/app/feature_analyses/slither_diagnostics.py
slither_lsp/app/logging/__init__.py
slither_lsp/app/logging/lsp_handler.py
slither_lsp/app/request_handlers/__init__.py
slither_lsp/app/request_handlers/call_hierarchy.py
slither_lsp/app/request_handlers/code_lens.py
slither_lsp/app/request_handlers/goto_def_impl_refs.py
slither_lsp/app/request_handlers/inlay_hints.py
slither_lsp/app/request_handlers/symbols.py
slither_lsp/app/request_handlers/type_hierarchy.py
slither_lsp/app/request_handlers/types.py
slither_lsp/app/request_handlers/analysis/__init__.py
slither_lsp/app/request_handlers/analysis/get_detector_list.py
slither_lsp/app/request_handlers/analysis/get_version.py
slither_lsp/app/request_handlers/compilation/__init__.py
slither_lsp/app/request_handlers/compilation/get_command_line_args.py
slither_lsp/app/types/analysis_structures.py
slither_lsp/app/types/params.py
slither_lsp/app/utils/file_paths.py
slither_lsp/app/utils/ranges.py
slither_lsp-0.0.1.dist-info/LICENSE
slither_lsp-0.0.1.dist-info/METADATA
slither_lsp-0.0.1.dist-info/WHEEL
slither_lsp-0.0.1.dist-info/entry_points.txt
slither_lsp-0.0.1.dist-info/top_level.txt
slither_lsp-0.0.1.dist-info/RECORD
