Metadata-Version: 2.1
Name: slither-lsp
Version: 0.0.1
Summary: Language Server powered by the Slither static analyzer
Author-email: Trail of Bits <opensource@trailofbits.com>
License: GNU AFFERO GENERAL PUBLIC LICENSE
Project-URL: Repository, https://github.com/crytic/slither-lsp
Project-URL: Issues, https://github.com/crytic/slither-lsp/issues
Classifier: License :: OSI Approved :: GNU Affero General Public License v3
Classifier: Intended Audience :: Developers
Classifier: Programming Language :: Python :: 3 :: Only
Classifier: Topic :: Security
Requires-Python: >=3.10
License-File: LICENSE
Requires-Dist: slither-analyzer >=0.10.2
Requires-Dist: semantic-version >=2.10.0
Requires-Dist: pygls >=1.3.0
